Metadata-Version: 2.1
Name: zcollection
Version: 2024.2.0
Summary: Zarr Collection
Home-page: https://github.com/CNES/zcollection
Author: CNES/CLS
Author-email: fbriol@gmail.com
License: BSD License
Keywords: zarr,collection,xarray,dask
Classifier: Development Status :: 5 - Production/Stable
Classifier: Intended Audience :: Science/Research
Classifier: Natural Language :: English
Classifier: Operating System :: MacOS
Classifier: Operating System :: Microsoft :: Windows
Classifier: Operating System :: POSIX
Classifier: Programming Language :: Python :: 3.8
Classifier: Programming Language :: Python :: 3.9
Classifier: Programming Language :: Python :: 3.10
Classifier: Programming Language :: Python :: 3.11
Classifier: Programming Language :: Python :: 3.12
Classifier: Topic :: Scientific/Engineering :: Physics
Requires-Python: >=3.8
License-File: LICENSE
Requires-Dist: dask>=2022.8.0
Requires-Dist: distributed
Requires-Dist: fasteners
Requires-Dist: fsspec
Requires-Dist: numcodecs
Requires-Dist: numpy>=1.20
Requires-Dist: pandas
Requires-Dist: xarray
Requires-Dist: zarr>=2.11
Provides-Extra: test
Requires-Dist: pytest; extra == "test"
Requires-Dist: pytest-cov; extra == "test"
